asparagus/__init__.py
asparagus/middleware.py
asparagus-0.1.0.dist-info/DESCRIPTION.rst
asparagus-0.1.0.dist-info/METADATA
asparagus-0.1.0.dist-info/RECORD
asparagus-0.1.0.dist-info/WHEEL
asparagus-0.1.0.dist-info/metadata.json
asparagus-0.1.0.dist-info/top_level.txt
