Metadata-Version: 2.0
Name: asparagus
Version: 0.1.0
Summary: Django middleware to log object leaks
Home-page: https://github.com/wildfoundry/django-asparagust
Author: Wildfoundry
Author-email: will.mcgugan@wildfoundry.com
License: LGPL
Keywords: django leak
Platform: UNKNOWN
Classifier: Development Status :: 3 - Alpha
Classifier: Intended Audience :: Developers
Classifier: Topic :: Software Development :: Bug Tracking
Classifier: Framework :: Django
Classifier: License :: OSI Approved :: GNU Library or Lesser General Public License (LGPL)
Classifier: Programming Language :: Python :: 3.5
Requires-Dist: objgraph
